{
  "device": {
    "0": {
      "name": "devding",
      "reboottime": "1h",
      "description": "IoT Dev-Ding"
    }
  },

  "ota": {
    "0": {
      "port": 8266,
      "no-passwd": "123",
      "description": "Listen for 'over the air' OTA Updates"
    }
  },

  "ssdp": {
    "0": {
      "ModelUrl": "https://www.mathertel.de/Arduino"
    }
  },

  "ntptime": {
    "0": {
      "readtime": "10m",
      "zone": 2
    }
  },

  "DisplaySSD1306": {
    "0": {
      "address": "60",
      "SDA": 5,
      "SCL": 4,
      "height": 64
    }
  }
}